temptation/__init__.py
temptation/default_resolvers.py
temptation/template.py
temptation-0.1.1.data/scripts/temptation
temptation-0.1.1.dist-info/DESCRIPTION.rst
temptation-0.1.1.dist-info/METADATA
temptation-0.1.1.dist-info/RECORD
temptation-0.1.1.dist-info/WHEEL
temptation-0.1.1.dist-info/metadata.json
temptation-0.1.1.dist-info/top_level.txt
