Metadata-Version: 2.0
Name: temptation
Version: 0.1.1
Summary: Temptation is a simple and straightforward template engine supporting semantic substitution expressions.
Home-page: https://github.com/yaccob/temptation
Author: Jakob Stemberger
Author-email: yaccob@gmx.net
License: Apache 2.0
Download-URL: https://github.com/yaccob/temptation/archive/0.1.1.tar.gz
Keywords: temptation,template-engine,template,yaml,json,transform,jsonpath,json-path
Platform: UNKNOWN
Classifier: Programming Language :: Python :: 2.7
Requires-Dist: PyYaml
Requires-Dist: jsonpath-ng
